trigonometry.py
trigonometry-1.0.dist-info/METADATA
trigonometry-1.0.dist-info/WHEEL
trigonometry-1.0.dist-info/top_level.txt
trigonometry-1.0.dist-info/RECORD
