Metadata-Version: 2.1
Name: trigonometry
Version: 1.0
Summary: A package that can calculate trigonometric functions 
Home-page: https://github.com/guna-j16/trigonometry
Author: Gunasekaran.J, Venkateswar.S
Author-email: guna.j16@outlook.com
License: UNKNOWN
Platform: UNKNOWN
Classifier: Programming Language :: Python :: 3.5
Classifier: Programming Language :: Python :: 3.6
Classifier: Programming Language :: Python :: 3.7
Classifier: Programming Language :: Python :: 3.8
Classifier: Operating System :: OS Independent
